rsendmail.py
sshsendmail.py
rsendmail-1.1.4.dist-info/LICENSE.rst
rsendmail-1.1.4.dist-info/METADATA
rsendmail-1.1.4.dist-info/WHEEL
rsendmail-1.1.4.dist-info/entry_points.txt
rsendmail-1.1.4.dist-info/top_level.txt
rsendmail-1.1.4.dist-info/RECORD
